data_science_toolkit/__init__.py
data_science_toolkit/chart.py
data_science_toolkit/csm.py
data_science_toolkit/dataframe.py
data_science_toolkit/gis.py
data_science_toolkit/imagefactory.py
data_science_toolkit/lib.py
data_science_toolkit/model.py
data_science_toolkit/r3.py
data_science_toolkit/rl.py
data_science_toolkit/rl_dqn.py
data_science_toolkit/vectorizer.py
data_science_toolkit-0.1.65.dist-info/LICENSE
data_science_toolkit-0.1.65.dist-info/METADATA
data_science_toolkit-0.1.65.dist-info/WHEEL
data_science_toolkit-0.1.65.dist-info/top_level.txt
data_science_toolkit-0.1.65.dist-info/RECORD
