Metadata-Version: 2.1
Name: data-science-toolkit
Version: 0.1.65
Summary: Data Science Toolkit (DST) is a Python library that helps implement data science related project with ease.
Home-page: https://github.com/elhachimi-ch/dst
Author: EL HACHIMI CHOUAIB
Author-email: elhachimi.ch@gmail.com
Project-URL: Bug Tracker, https://github.com/elhachimi-ch/dst/issues
Classifier: Programming Language :: Python :: 3
Classifier: License :: OSI Approved :: MIT License
Classifier: Operating System :: OS Independent
Requires-Python: >=3.5
License-File: LICENSE
Requires-Dist: setuptools >=42
Requires-Dist: wheel
Requires-Dist: pandas
Requires-Dist: numpy ==1.25
Requires-Dist: tensorflow
Requires-Dist: scikit-learn
Requires-Dist: seaborn
Requires-Dist: matplotlib
Requires-Dist: wordcloud
Requires-Dist: keras
Requires-Dist: plotly
Requires-Dist: xgboost
Requires-Dist: opencv-python
Requires-Dist: scikit-image
Requires-Dist: unidecode
Requires-Dist: emoji >=1.7
Requires-Dist: textblob
Requires-Dist: nltk
Requires-Dist: optuna
Requires-Dist: xarray
Requires-Dist: openpyxl
Requires-Dist: catboost
